{
    "requestId": "f8fb0a8f5ec34f4a8c34afc2a19e7392",
    "code": "0000",
    "msg": "Success",
    "recordsTotal": null,
    "data": {
        "id": 15745290141290496,
        "createTime": 1631501169703,
        "updateTime": 1631673893216,
        "type": "DRAMA_COMMENT",
        "typeId": 32904,
        "authorId": 183961903,
        "score": 10.0,
        "content": "男的帅女的美！配一脸！这种假戏真做的梗永远吃不完！爱死这两只小可爱啦",
        "images": [{
            "url": "http://img.rr.tv/img/img/20210913/o_a24fb25dfe0546e68d1aab2c0c923e71.webp",
            "height": 719.0,
            "width": 1080.0
        }],
        "liked": false,
        "likeCount": 11,
        "realLikeCount": 11,
        "replyCount": 11,
        "deleted": false,
        "author": {
            "id": 183961903,
            "createTime": 1628149259000,
            "updateTime": 1634787343000,
            "loginName": "13585710960#5919449631",
            "nickName": "奈奈一一一一",
            "mobile": "13585710960",
            "sex": 0,
            "birthday": "2000-01-01",
            "city": "",
            "intro": "",
            "headImgUrl": "http://img.rr.tv/img/head/20211021/o_73a3ef5402aa47ba8fc3f311a7ad79f9.jpg",
            "bgImgUrl": null,
            "isConfirmed": false,
            "confirmInfo": "",
            "isLock": false,
            "roleInfo": "normal",
            "level": 4,
            "score": 1111,
            "sign": "",
            "certLabel": null,
            "certNote": null,
            "deviceId": "7d08f87e-e42f-4ead-8a25-5871a42b3e5b",
            "userCode": "5919449631",
            "medalList": [{
                "id": 1,
                "createTime": 1635389835000,
                "updateTime": 1635389835000,
                "userId": 183961903,
                "medalId": 1,
                "beginTime": 1635389836000,
                "endTime": 1644029836000,
                "medalView": {
                    "id": 1,
                    "createTime": 1501052800000,
                    "updateTime": 1604657316000,
                    "imgUrl": "http://img.rr.tv/cover/20200424/o_1587720799676.png",
                    "name": "大魔王",
                    "orderNum": 100,
                    "description": "原大魔王勋章已升级为人人VIP，请于我的／VIP页面，查看特权详情及有效期，本勋章页面仅供纪念。",
                    "getWay": "开通勋章",
                    "costType": null,
                    "cost": 100,
                    "durationDays": 7,
                    "getUrl": "HTML https://mobile.rr.tv/fe/#/view/medalsale/main",
                    "spec": "[{\"description\":\"7天\",\"durationDays\":\"7\",\"cost\":\"999999\"},{\"description\":\"30天\",\"durationDays\":\"30\",\"cost\":\"999999\"},{\"description\":\"100天\",\"durationDays\":\"100\",\"cost\":\"500\"}]",
                    "type": 1,
                    "assembly": false,
                    "visible": true,
                    "medalPrivilegeViewList": [{
                        "id": 1450,
                        "createTime": 1605864297000,
                        "updateTime": 1605864297000,
                        "medalId": 1,
                        "privilegeId": 1,
                        "privilegeView": {
                            "id": 1,
                            "createTime": 1500961022000,
                            "updateTime": 1523534454000,
                            "effectObject": "video",
                            "action": "play",
                            "function": "originalPainting",
                            "description": "解锁原画",
                            "icon": "jiesuoyuanhua"
                        }
                    }, {
                        "id": 1451,
                        "createTime": 1605864297000,
                        "updateTime": 1605864297000,
                        "medalId": 1,
                        "privilegeId": 4,
                        "privilegeView": {
                            "id": 4,
                            "createTime": 1503027132000,
                            "updateTime": 1523534454000,
                            "effectObject": "video",
                            "action": "play",
                            "function": "noLimit",
                            "description": "看剧无限制",
                            "icon": "kanjuwuxianzhi"
                        }
                    }, {
                        "id": 1452,
                        "createTime": 1605864297000,
                        "updateTime": 1605864297000,
                        "medalId": 1,
                        "privilegeId": 23,
                        "privilegeView": {
                            "id": 23,
                            "createTime": 1506396640000,
                            "updateTime": 1523534454000,
                            "effectObject": "video",
                            "action": "play",
                            "function": "noAd",
                            "description": "看剧无广告",
                            "icon": "kanjuwuguanggao"
                        }
                    }, {
                        "id": 1453,
                        "createTime": 1605864297000,
                        "updateTime": 1605864297000,
                        "medalId": 1,
                        "privilegeId": 43,
                        "privilegeView": {
                            "id": 43,
                            "createTime": 1553774003000,
                            "updateTime": 1554281456000,
                            "effectObject": "danmu",
                            "action": "send",
                            "function": "superBarrageBlue",
                            "description": "超级弹幕",
                            "icon": "chaojidanmu"
                        }
                    }, {
                        "id": 1454,
                        "createTime": 1605864297000,
                        "updateTime": 1605864297000,
                        "medalId": 1,
                        "privilegeId": 46,
                        "privilegeView": {
                            "id": 46,
                            "createTime": 1574992769000,
                            "updateTime": 1574992769000,
                            "effectObject": "video",
                            "action": "play",
                            "function": "vipVideo",
                            "description": "勋章专享剧集",
                            "icon": "zhuanxiangjuji"
                        }
                    }, {
                        "id": 1455,
                        "createTime": 1605864297000,
                        "updateTime": 1605864297000,
                        "medalId": 1,
                        "privilegeId": 45,
                        "privilegeView": {
                            "id": 45,
                            "createTime": 1571106421000,
                            "updateTime": 1571106421000,
                            "effectObject": "mall",
                            "action": "sale",
                            "function": "mallDiscount",
                            "description": "龙醇商城九折",
                            "icon": "longchunshangcheng"
                        }
                    }, {
                        "id": 1456,
                        "createTime": 1605864297000,
                        "updateTime": 1605864297000,
                        "medalId": 1,
                        "privilegeId": 37,
                        "privilegeView": {
                            "id": 37,
                            "createTime": 1511245183000,
                            "updateTime": 1558428196000,
                            "effectObject": "growth",
                            "action": "play",
                            "function": "0.4",
                            "description": "看剧经验+40%",
                            "icon": "jingyanzhijiacheng"
                        }
                    }, {
                        "id": 1457,
                        "createTime": 1605864297000,
                        "updateTime": 1605864297000,
                        "medalId": 1,
                        "privilegeId": 25,
                        "privilegeView": {
                            "id": 25,
                            "createTime": 1506398041000,
                            "updateTime": 1523534454000,
                            "effectObject": "nickName",
                            "action": "show",
                            "function": "nameHighLight",
                            "description": "高亮昵称",
                            "icon": "gaoliangnicheng"
                        }
                    }, {
                        "id": 1458,
                        "createTime": 1605864297000,
                        "updateTime": 1605864297000,
                        "medalId": 1,
                        "privilegeId": 24,
                        "privilegeView": {
                            "id": 24,
                            "createTime": 1506396702000,
                            "updateTime": 1612767087000,
                            "effectObject": "comment",
                            "action": "write",
                            "function": "highLight",
                            "description": "高亮评论回复",
                            "icon": "huifu"
                        }
                    }, {
                        "id": 1459,
                        "createTime": 1605864297000,
                        "updateTime": 1605864297000,
                        "medalId": 1,
                        "privilegeId": 20,
                        "privilegeView": {
                            "id": 20,
                            "createTime": 1503647083000,
                            "updateTime": 1523534454000,
                            "effectObject": "article",
                            "action": "write",
                            "function": "highLight",
                            "description": "高亮发帖",
                            "icon": "gaoliangfatie"
                        }
                    }]
                },
                "display": null
            }, {
                "id": 39,
                "createTime": 1634886407000,
                "updateTime": 1634886407000,
                "userId": 183961903,
                "medalId": 39,
                "beginTime": 1634886408000,
                "endTime": 1637478408000,
                "medalView": {
                    "id": 39,
                    "createTime": 1634030573000,
                    "updateTime": 1634030573000,
                    "imgUrl": "http://img.rr.tv/img/img/20211012/o_b2bfe0230ade429e91a72b9e08746e1e.png",
                    "name": "社区共建者",
                    "orderNum": 1,
                    "description": "活动期间积极体验社区功能，认真填写内测问卷；或参加社区有奖活动，产出优质内容即可获得",
                    "getWay": "特殊活动产出",
                    "costType": null,
                    "cost": null,
                    "durationDays": 30,
                    "getUrl": "NONE ",
                    "spec": null,
                    "type": 1,
                    "assembly": false,
                    "visible": true,
                    "medalPrivilegeViewList": [{
                        "id": 1552,
                        "createTime": 1634030573000,
                        "updateTime": 1634030573000,
                        "medalId": 39,
                        "privilegeId": 29,
                        "privilegeView": {
                            "id": 29,
                            "createTime": 1507635029000,
                            "updateTime": 1558428196000,
                            "effectObject": "growth",
                            "action": "play",
                            "function": "0.15",
                            "description": "看剧经验+15%",
                            "icon": "jingyanzhijiacheng"
                        }
                    }]
                },
                "display": null
            }],
            "vipLevel": {
                "id": 4518238,
                "userId": 183961903,
                "level": "0",
                "expiredTime": 1644029836000,
                "createTime": 1636342049000,
                "received": "0",
                "durationDays": null
            }
        },
        "drama": {
            "id": 32904,
            "name": "和我结婚吧！",
            "dramaType": "TV",
            "plotTypeList": ["剧情", "喜剧", "爱情"],
            "subtitle": "国家分配男友",
            "language": "日语",
            "producerRegionList": ["日本"],
            "cover": "http://img.rr.tv/seasonCover/20210319/o_1616148359110.jpg",
            "actorList": ["久间田琳加/濑户利树/水泽林太郎/柾木玲弥/高桥瞳/纲启永/佐藤晴美/温水洋一/神保悟志"],
            "directorList": [""],
            "score": 8.2,
            "year": "2020",
            "alias": "和我结婚吧！",
            "enable": true,
            "seasonNo": null
        }
    }
}
